pathik/__init__.py
pathik/cli.py
pathik/crawler.py
pathik/safe_api.py
pathik/schema.py
pathik/simple.py
pathik/bin/.gitkeep
pathik-0.3.1.dist-info/licenses/LICENSE
pathik-0.3.1.dist-info/METADATA
pathik-0.3.1.dist-info/WHEEL
pathik-0.3.1.dist-info/entry_points.txt
pathik-0.3.1.dist-info/top_level.txt
pathik-0.3.1.dist-info/RECORD
