Metadata-Version: 2.4
Name: pathik
Version: 0.3.1
Summary: A web crawler implemented in Go with Python bindings
Home-page: https://github.com/justrach/pathik
Author: Your Name
Author-email: your.email@example.com
Classifier: Programming Language :: Python :: 3
Classifier: License :: OSI Approved :: MIT License
Classifier: Operating System :: OS Independent
Requires-Python: >=3.6
License-File: LICENSE
Requires-Dist: requests>=2.25.0
Requires-Dist: tqdm>=4.50.0
Provides-Extra: kafka
Requires-Dist: kafka-python>=2.0.0; extra == "kafka"
Dynamic: author
Dynamic: author-email
Dynamic: classifier
Dynamic: description
Dynamic: description-content-type
Dynamic: home-page
Dynamic: license-file
Dynamic: provides-extra
Dynamic: requires-dist
Dynamic: requires-python
Dynamic: summary
